{"next":null,"previous":null,"total":6,"results":[{"toolId":"078f6935-8e05-4d95-bedf-b89ee12c25fd","name":"warmTransfer","created":"2025-12-06T00:49:49.862165Z","definition":{"description":"Transfers the call to another party.","dynamicParameters":[{"name":"context","location":"PARAMETER_LOCATION_BODY","schema":{"description":"Any context from the conversation that needs to be shared with the new party to get them up to speed.","type":"string"}}],"staticParameters":[{"name":"target","location":"PARAMETER_LOCATION_BODY","value":"transfer_target"},{"name":"transferSystemPromptTemplate","location":"PARAMETER_LOCATION_BODY","value":"You just called this user in order to transfer an earlier caller to them.  You have this context from the earlier caller:\n\n{context}\n\nWhen the user is ready to be connected with the earlier caller, invoke `acceptTransfer` to connect them. If the user does not want to talk to the earlier caller, use `rejectTransfer` with an appropriate reason instead. In the latter case, be sure to include any details you need to share with the earlier caller about why the transfer could not be completed. Do not invoke either tool until the user has made their wishes known."},{"name":"transferType","location":"PARAMETER_LOCATION_BODY","value":"TRY_REFER"},{"name":"from","location":"PARAMETER_LOCATION_BODY","value":null},{"name":"username","location":"PARAMETER_LOCATION_BODY","value":null},{"name":"password","location":"PARAMETER_LOCATION_BODY","value":null},{"name":"holdMusicUrl","location":"PARAMETER_LOCATION_BODY","value":"https://storage.googleapis.com/fixie-web-public/defaultHold.mp3"},{"name":"inviteHeaders","location":"PARAMETER_LOCATION_BODY","value":{}},{"name":"referHeaders","location":"PARAMETER_LOCATION_BODY","value":{}}],"automaticParameters":[{"name":"callStageId","location":"PARAMETER_LOCATION_BODY","knownValue":"KNOWN_PARAM_CALL_STAGE_ID"}],"requirements":{"httpSecurityOptions":{"options":[{"ultravoxCallTokenRequirement":{"scopes":["transfer"]}}]},"requiredParameterOverrides":["target"]},"http":{"baseUrlPattern":"https://api.ultravox.ai/api/tool_impl/warm_transfer","httpMethod":"POST"},"modelToolName":"transferCall"},"ownership":"public"},{"toolId":"2fff509d-273f-414e-91ff-aa933435a545","name":"coldTransfer","created":"2025-10-29T19:29:46.056988Z","definition":{"description":"Transfers the call to another party.","staticParameters":[{"name":"target","location":"PARAMETER_LOCATION_BODY","value":"transfer_target"},{"name":"extraHeaders","location":"PARAMETER_LOCATION_BODY","value":{}},{"name":"sipVerb","location":"PARAMETER_LOCATION_BODY","value":"REFER"},{"name":"from","location":"PARAMETER_LOCATION_BODY","value":null},{"name":"username","location":"PARAMETER_LOCATION_BODY","value":null},{"name":"password","location":"PARAMETER_LOCATION_BODY","value":null},{"name":"holdMusicUrl","location":"PARAMETER_LOCATION_BODY","value":"https://storage.googleapis.com/fixie-web-public/defaultHold.mp3"}],"requirements":{"httpSecurityOptions":{"options":[{"ultravoxCallTokenRequirement":{"scopes":["transfer"]}}]},"requiredParameterOverrides":["target"]},"http":{"baseUrlPattern":"https://api.ultravox.ai/api/tool_impl/cold_transfer","httpMethod":"POST"},"modelToolName":"transferCall"},"ownership":"public"},{"toolId":"8721c74d-af3f-4dfa-a736-3bc170ef917c","name":"leaveVoicemail","created":"2025-05-22T16:28:34.340355Z","definition":{"description":"Leaves a voicemail and ends the call.","dynamicParameters":[{"name":"message","location":"PARAMETER_LOCATION_QUERY","schema":{"description":"The voicemail message to leave.","type":"string"},"required":true}],"staticParameters":[{"name":"strict","location":"PARAMETER_LOCATION_QUERY","value":true},{"name":"result","location":"PARAMETER_LOCATION_QUERY","value":"[Leaving voicemail...]"}],"http":{"baseUrlPattern":"https://api.ultravox.ai/api/tool_impl/hang_up","httpMethod":"GET"},"modelToolName":"leaveVoicemail","timeout":"2.500s","precomputable":true},"ownership":"public"},{"toolId":"84a31bac-5c1b-41c3-9058-f81acb7ffaa7","name":"queryCorpus","created":"2025-01-30T02:24:55.847052Z","definition":{"description":"Retrieves relevant information from an existing knowledge base.","dynamicParameters":[{"name":"query","location":"PARAMETER_LOCATION_BODY","schema":{"description":"What to search for.","type":"string"},"required":true},{"name":"max_results","location":"PARAMETER_LOCATION_BODY","schema":{"description":"How many documents to receive back. Defaults to 5, but may be between 1 and 20.","type":"integer","default":5.0}},{"name":"corpus_id","location":"PARAMETER_LOCATION_BODY","schema":{"description":"irrelevant - always replaced by override"},"required":true}],"staticParameters":[{"name":"minimum_score","location":"PARAMETER_LOCATION_BODY","value":0.0}],"requirements":{"httpSecurityOptions":{"options":[{"ultravoxCallTokenRequirement":{"scopes":["corpus"]}}]},"requiredParameterOverrides":["corpus_id"]},"http":{"baseUrlPattern":"https://api.ultravox.ai/api/tool_impl/query_corpus","httpMethod":"POST"},"modelToolName":"queryCorpus","precomputable":true},"ownership":"public"},{"toolId":"3e9489b1-25de-4032-bb3d-f7b84765ec93","name":"playDtmfSounds","created":"2025-01-14T17:52:27.021350Z","definition":{"description":"Synthesizes dual-tone multi-frequency tones corresponding to the given digits and plays the synthesized audio for the user.","dynamicParameters":[{"name":"digits","location":"PARAMETER_LOCATION_QUERY","schema":{"description":"The digits for which tones should be produced. May also include \"*\" or \"#\".","type":"string"},"required":true}],"staticParameters":[{"name":"toneDuration","location":"PARAMETER_LOCATION_QUERY","value":"0.2s"},{"name":"spaceDuration","location":"PARAMETER_LOCATION_QUERY","value":"0.1s"}],"automaticParameters":[{"name":"sampleRate","location":"PARAMETER_LOCATION_QUERY","knownValue":"KNOWN_PARAM_OUTPUT_SAMPLE_RATE"}],"requirements":{"httpSecurityOptions":{"options":[{"ultravoxCallTokenRequirement":{"scopes":["dtmf"]}}]}},"http":{"baseUrlPattern":"https://api.ultravox.ai/api/tool_impl/dtmf","httpMethod":"GET"},"modelToolName":"playDtmfSounds"},"ownership":"public"},{"toolId":"56294126-5a7d-4948-b67d-3b7e13d55ea7","name":"hangUp","created":"2024-12-16T23:32:12.971676Z","definition":{"description":"A tool that ends the current call once completed","dynamicParameters":[{"name":"reason","location":"PARAMETER_LOCATION_QUERY","schema":{"description":"A brief reason for hanging up.","type":"string"}}],"staticParameters":[{"name":"strict","location":"PARAMETER_LOCATION_QUERY","value":true}],"http":{"baseUrlPattern":"https://api.ultravox.ai/api/tool_impl/hang_up","httpMethod":"get"},"modelToolName":"hangUp","precomputable":true},"ownership":"public"}]}